dataasset/__init__.py
dataasset/__main__.py
dataasset/alembic/README
dataasset/alembic/env.py
dataasset/alembic/script.py.mako
dataasset/alembic/versions/ab6e9a8419c2_initial_migration.py
dataasset/alembic.ini
dataasset/application.py
dataasset/asset.py
dataasset/db.py
dataasset/factory.py
dataasset/io.py
dataasset/migrations.py
dataasset/model.py
dataasset/repository.py
dataasset-0.4.6.dist-info/entry_points.txt
dataasset-0.4.6.dist-info/WHEEL
dataasset-0.4.6.dist-info/METADATA
dataasset-0.4.6.dist-info/RECORD
