Metadata-Version: 2.1
Name: dataasset
Version: 0.4.6
Summary: 
Author: c-jamie
Author-email: jamie.b.clery@gmail.com
Requires-Python: >=3.9,<4.0
Classifier: Programming Language :: Python :: 3
Classifier: Programming Language :: Python :: 3.9
Classifier: Programming Language :: Python :: 3.10
Classifier: Programming Language :: Python :: 3.11
Provides-Extra: mssql
Provides-Extra: mysql
Provides-Extra: postgres
Requires-Dist: SQLAlchemy (>=1.4,<2.0); extra == "postgres" or extra == "mysql" or extra == "mssql"
Requires-Dist: alembic (>=1.8,<2.0); extra == "postgres" or extra == "mysql" or extra == "mssql"
Requires-Dist: psycopg2 (>=2.9,<3.0); extra == "postgres"
Requires-Dist: pymysql (>=1.0,<2.0); extra == "mysql"
Requires-Dist: pyodbc (>=4.0.34,<5.0.0); extra == "mssql"
Requires-Dist: sqlalchemy-json (>=0.5,<0.6); extra == "postgres" or extra == "mysql" or extra == "mssql"
